term_pkg/__init__.py
term_pkg/beep-07.wav
term_pkg/classic_hurt.mp3
term_pkg/heart.py
term_pkg/system_control.py
terminal_pkg_Team3SP20-1.0.1.dist-info/LICENSE
terminal_pkg_Team3SP20-1.0.1.dist-info/METADATA
terminal_pkg_Team3SP20-1.0.1.dist-info/WHEEL
terminal_pkg_Team3SP20-1.0.1.dist-info/top_level.txt
terminal_pkg_Team3SP20-1.0.1.dist-info/RECORD
