Metadata-Version: 2.1
Name: terminal-pkg-Team3SP20
Version: 1.0.1
Summary: Files for cafeteria terminal prototype
Home-page: https://github.com/MVNUCS/TeamThreeSP20
Author: Team3SP20
Author-email: dansharp94@mail.mvnu.edu
License: UNKNOWN
Platform: UNKNOWN
Classifier: Programming Language :: Python :: 3
Classifier: License :: OSI Approved :: MIT License
Classifier: Operating System :: OS Independent
Requires-Python: >=3.6
